[{"CaseId":1,"CreatedOn":"2023-10-25 07:02","Description":"","EditedOn":"2024-01-31 10:35","EndingYear":"2068","FixResultFileName":"False","FixResultInfo":{"WorkTimesFolderPath":null,"GdxElasticDermands":{"GdxSelectedFile":{"FileName":"","FilePath":"","IsSelected":false},"IsApplied":false},"GdxIre":{"GdxSelectedFile":{"FileName":"","FilePath":"","IsSelected":false},"IsApplied":false,"RadioSelection":1},"GdxUseSolution":{"FixYearsUpto":"","GdxSelectedFile":{"FileName":"","FilePath":"","IsSelected":false},"IsApplied":false,"RadioSelection":1},"IsApplyFixResult":false},"GAMSSourceFolder":"GAMS_SrcTIMES.v4.7.0","Name":"NZ_NDCLO","ParametricGroup":null,"ParametricGroupId":null,"PeriodsDefinition":"pdef-70","PropertiesGroup":"DefaultProperties","PropertiesGroupId":3,"RegionGroup":"AllRegion","RegionGroupId":2,"ScenarioGroup":"NZ_NDCLO","ScenarioGroupId":35,"Solver":"cplex","SolverOptionFile":"2BS_Con_Aut","UserName":"bruno"},{"CaseId":2,"CreatedOn":"2023-10-25 07:03","Description":"","EditedOn":"2024-01-31 10:35","EndingYear":"2068","FixResultFileName":"False","FixResultInfo":{"WorkTimesFolderPath":null,"GdxElasticDermands":{"GdxSelectedFile":{"FileName":"","FilePath":"","IsSelected":false},"IsApplied":false},"GdxIre":{"GdxSelectedFile":{"FileName":"","FilePath":"","IsSelected":false},"IsApplied":false,"RadioSelection":1},"GdxUseSolution":{"FixYearsUpto":"","GdxSelectedFile":{"FileName":"","FilePath":"","IsSelected":false},"IsApplied":false,"RadioSelection":1},"IsApplyFixResult":false},"GAMSSourceFolder":"GAMS_SrcTIMES.v4.7.0","Name":"NZ_NDCUP","ParametricGroup":null,"ParametricGroupId":null,"PeriodsDefinition":"pdef-70","PropertiesGroup":"DefaultProperties","PropertiesGroupId":3,"RegionGroup":"AllRegion","RegionGroupId":2,"ScenarioGroup":"NZ_NDCUP","ScenarioGroupId":19,"Solver":"cplex","SolverOptionFile":"2BS_Con_Aut","UserName":"bruno"},{"CaseId":3,"CreatedOn":"2023-11-28 08:29","Description":"","EditedOn":"2024-01-31 10:35","EndingYear":"2068","FixResultFileName":"False","FixResultInfo":{"WorkTimesFolderPath":null,"GdxElasticDermands":{"GdxSelectedFile":{"FileName":"","FilePath":"","IsSelected":false},"IsApplied":false},"GdxIre":{"GdxSelectedFile":{"FileName":"","FilePath":"","IsSelected":false},"IsApplied":false,"RadioSelection":1},"GdxUseSolution":{"FixYearsUpto":"","GdxSelectedFile":{"FileName":"","FilePath":"","IsSelected":false},"IsApplied":false,"RadioSelection":1},"IsApplyFixResult":false},"GAMSSourceFolder":"GAMS_SrcTIMES.v4.7.0","Name":"REF","ParametricGroup":null,"ParametricGroupId":null,"PeriodsDefinition":"pdef-70","PropertiesGroup":"DefaultProperties","PropertiesGroupId":3,"RegionGroup":"AllRegion","RegionGroupId":2,"ScenarioGroup":"REF","ScenarioGroupId":30,"Solver":"cplex","SolverOptionFile":"2BS_Con_Aut","UserName":"bruno"},{"CaseId":4,"CreatedOn":"2024-01-25 16:34","Description":"","EditedOn":"2024-02-06 08:41","EndingYear":"2068","FixResultFileName":"False","FixResultInfo":{"WorkTimesFolderPath":null,"GdxElasticDermands":{"GdxSelectedFile":{"FileName":"","FilePath":"","IsSelected":false},"IsApplied":false},"GdxIre":{"GdxSelectedFile":{"FileName":"","FilePath":"","IsSelected":false},"IsApplied":false,"RadioSelection":1},"GdxUseSolution":{"FixYearsUpto":"","GdxSelectedFile":{"FileName":"","FilePath":"","IsSelected":false},"IsApplied":false,"RadioSelection":1},"IsApplyFixResult":false},"GAMSSourceFolder":"GAMS_SrcTIMES.v4.7.0","Name":"NZ10_2099B_99NESSNXCTCL","ParametricGroup":null,"ParametricGroupId":null,"PeriodsDefinition":"pdef-70","PropertiesGroup":"DefaultProperties","PropertiesGroupId":3,"RegionGroup":"AllRegion","RegionGroupId":2,"ScenarioGroup":"NZ10_2099B_99NESSNXCTCL","ScenarioGroupId":46,"Solver":"cplex","SolverOptionFile":"2BS_Con_Aut","UserName":"bruno"},{"CaseId":5,"CreatedOn":"2024-01-25 16:36","Description":"","EditedOn":"2024-02-01 19:21","EndingYear":"2068","FixResultFileName":"False","FixResultInfo":{"WorkTimesFolderPath":null,"GdxElasticDermands":{"GdxSelectedFile":{"FileName":"","FilePath":"","IsSelected":false},"IsApplied":false},"GdxIre":{"GdxSelectedFile":{"FileName":"","FilePath":"","IsSelected":false},"IsApplied":false,"RadioSelection":1},"GdxUseSolution":{"FixYearsUpto":"","GdxSelectedFile":{"FileName":"","FilePath":"","IsSelected":false},"IsApplied":false,"RadioSelection":1},"IsApplyFixResult":false},"GAMSSourceFolder":"GAMS_SrcTIMES.v4.7.0","Name":"NZ10_2099B_99EESSNXCNSC","ParametricGroup":null,"ParametricGroupId":null,"PeriodsDefinition":"pdef-70","PropertiesGroup":"DefaultProperties","PropertiesGroupId":3,"RegionGroup":"AllRegion","RegionGroupId":2,"ScenarioGroup":"NZ10_2099B_99EESSNXCNSC","ScenarioGroupId":54,"Solver":"cplex","SolverOptionFile":"2BS_Con_Aut","UserName":"bruno"},{"CaseId":6,"CreatedOn":"2024-01-25 16:37","Description":"","EditedOn":"2024-02-01 19:21","EndingYear":"2068","FixResultFileName":"False","FixResultInfo":{"WorkTimesFolderPath":null,"GdxElasticDermands":{"GdxSelectedFile":{"FileName":"","FilePath":"","IsSelected":false},"IsApplied":false},"GdxIre":{"GdxSelectedFile":{"FileName":"","FilePath":"","IsSelected":false},"IsApplied":false,"RadioSelection":1},"GdxUseSolution":{"FixYearsUpto":"","GdxSelectedFile":{"FileName":"","FilePath":"","IsSelected":false},"IsApplied":false,"RadioSelection":1},"IsApplyFixResult":false},"GAMSSourceFolder":"GAMS_SrcTIMES.v4.7.0","Name":"NZ10_2099A_99NESSNXCTCL","ParametricGroup":null,"ParametricGroupId":null,"PeriodsDefinition":"pdef-70","PropertiesGroup":"DefaultProperties","PropertiesGroupId":3,"RegionGroup":"AllRegion","RegionGroupId":2,"ScenarioGroup":"NZ10_2099A_99NESSNXCTCL","ScenarioGroupId":52,"Solver":"cplex","SolverOptionFile":"2BS_Con_Aut","UserName":"bruno"},{"CaseId":7,"CreatedOn":"2024-01-25 16:39","Description":"","EditedOn":"2024-02-01 19:21","EndingYear":"2068","FixResultFileName":"False","FixResultInfo":{"WorkTimesFolderPath":null,"GdxElasticDermands":{"GdxSelectedFile":{"FileName":"","FilePath":"","IsSelected":false},"IsApplied":false},"GdxIre":{"GdxSelectedFile":{"FileName":"","FilePath":"","IsSelected":false},"IsApplied":false,"RadioSelection":1},"GdxUseSolution":{"FixYearsUpto":"","GdxSelectedFile":{"FileName":"","FilePath":"","IsSelected":false},"IsApplied":false,"RadioSelection":1},"IsApplyFixResult":false},"GAMSSourceFolder":"GAMS_SrcTIMES.v4.7.0","Name":"NZ10_2099A_99NESSNXCNSC","ParametricGroup":null,"ParametricGroupId":null,"PeriodsDefinition":"pdef-70","PropertiesGroup":"DefaultProperties","PropertiesGroupId":3,"RegionGroup":"AllRegion","RegionGroupId":2,"ScenarioGroup":"NZ10_2099A_99NESSNXCNSC","ScenarioGroupId":4,"Solver":"cplex","SolverOptionFile":"2BS_Con_Aut","UserName":"bruno"},{"CaseId":8,"CreatedOn":"2024-01-25 16:39","Description":"","EditedOn":"2024-02-01 19:21","EndingYear":"2068","FixResultFileName":"False","FixResultInfo":{"WorkTimesFolderPath":null,"GdxElasticDermands":{"GdxSelectedFile":{"FileName":"","FilePath":"","IsSelected":false},"IsApplied":false},"GdxIre":{"GdxSelectedFile":{"FileName":"","FilePath":"","IsSelected":false},"IsApplied":false,"RadioSelection":1},"GdxUseSolution":{"FixYearsUpto":"","GdxSelectedFile":{"FileName":"","FilePath":"","IsSelected":false},"IsApplied":false,"RadioSelection":1},"IsApplyFixResult":false},"GAMSSourceFolder":"GAMS_SrcTIMES.v4.7.0","Name":"NZ10_2099A_99EESSNXCNSC","ParametricGroup":null,"ParametricGroupId":null,"PeriodsDefinition":"pdef-70","PropertiesGroup":"DefaultProperties","PropertiesGroupId":3,"RegionGroup":"AllRegion","RegionGroupId":2,"ScenarioGroup":"NZ10_2099A_99EESSNXCNSC","ScenarioGroupId":53,"Solver":"cplex","SolverOptionFile":"2BS_Con_Aut","UserName":"bruno"},{"CaseId":9,"CreatedOn":"2024-01-25 18:25","Description":"","EditedOn":"2024-02-28 16:41","EndingYear":"2068","FixResultFileName":"False","FixResultInfo":{"WorkTimesFolderPath":null,"GdxElasticDermands":{"GdxSelectedFile":{"FileName":"","FilePath":"","IsSelected":false},"IsApplied":false},"GdxIre":{"GdxSelectedFile":{"FileName":"","FilePath":"","IsSelected":false},"IsApplied":false,"RadioSelection":1},"GdxUseSolution":{"FixYearsUpto":"","GdxSelectedFile":{"FileName":"","FilePath":"","IsSelected":false},"IsApplied":false,"RadioSelection":1},"IsApplyFixResult":false},"GAMSSourceFolder":"GAMS_SrcTIMES.v4.7.0","Name":"NZ10_2055B_99EESSNXCTSC","ParametricGroup":null,"ParametricGroupId":null,"PeriodsDefinition":"pdef-70","PropertiesGroup":"DefaultProperties","PropertiesGroupId":3,"RegionGroup":"AllRegion","RegionGroupId":2,"ScenarioGroup":"NZ10_2055B_99EESSNXCTSC","ScenarioGroupId":57,"Solver":"cplex","SolverOptionFile":"2BS_Con_Aut","UserName":"bruno"},{"CaseId":10,"CreatedOn":"2024-01-25 18:27","Description":"","EditedOn":"2024-02-01 19:21","EndingYear":"2068","FixResultFileName":"False","FixResultInfo":{"WorkTimesFolderPath":null,"GdxElasticDermands":{"GdxSelectedFile":{"FileName":"","FilePath":"","IsSelected":false},"IsApplied":false},"GdxIre":{"GdxSelectedFile":{"FileName":"","FilePath":"","IsSelected":false},"IsApplied":false,"RadioSelection":1},"GdxUseSolution":{"FixYearsUpto":"","GdxSelectedFile":{"FileName":"","FilePath":"","IsSelected":false},"IsApplied":false,"RadioSelection":1},"IsApplyFixResult":false},"GAMSSourceFolder":"GAMS_SrcTIMES.v4.7.0","Name":"NZ10_2055A_99EESSNXCTSC","ParametricGroup":null,"ParametricGroupId":null,"PeriodsDefinition":"pdef-70","PropertiesGroup":"DefaultProperties","PropertiesGroupId":3,"RegionGroup":"AllRegion","RegionGroupId":2,"ScenarioGroup":"NZ10_2055A_99EESSNXCTSC","ScenarioGroupId":10,"Solver":"cplex","SolverOptionFile":"2BS_Con_Aut","UserName":"bruno"},{"CaseId":11,"CreatedOn":"2024-01-25 18:29","Description":"","EditedOn":"2024-02-01 19:21","EndingYear":"2068","FixResultFileName":"False","FixResultInfo":{"WorkTimesFolderPath":null,"GdxElasticDermands":{"GdxSelectedFile":{"FileName":"","FilePath":"","IsSelected":false},"IsApplied":false},"GdxIre":{"GdxSelectedFile":{"FileName":"","FilePath":"","IsSelected":false},"IsApplied":false,"RadioSelection":1},"GdxUseSolution":{"FixYearsUpto":"","GdxSelectedFile":{"FileName":"","FilePath":"","IsSelected":false},"IsApplied":false,"RadioSelection":1},"IsApplyFixResult":false},"GAMSSourceFolder":"GAMS_SrcTIMES.v4.7.0","Name":"NZ10_2055A_11EESSNXCTSC","ParametricGroup":null,"ParametricGroupId":null,"PeriodsDefinition":"pdef-70","PropertiesGroup":"DefaultProperties","PropertiesGroupId":3,"RegionGroup":"AllRegion","RegionGroupId":2,"ScenarioGroup":"NZ10_2055A_11EESSNXCTSC","ScenarioGroupId":11,"Solver":"cplex","SolverOptionFile":"2BS_Con_Aut","UserName":"bruno"},{"CaseId":12,"CreatedOn":"2024-01-25 18:37","Description":"","EditedOn":"2024-02-01 19:21","EndingYear":"2068","FixResultFileName":"False","FixResultInfo":{"WorkTimesFolderPath":null,"GdxElasticDermands":{"GdxSelectedFile":{"FileName":"","FilePath":"","IsSelected":false},"IsApplied":false},"GdxIre":{"GdxSelectedFile":{"FileName":"","FilePath":"","IsSelected":false},"IsApplied":false,"RadioSelection":1},"GdxUseSolution":{"FixYearsUpto":"","GdxSelectedFile":{"FileName":"","FilePath":"","IsSelected":false},"IsApplied":false,"RadioSelection":1},"IsApplyFixResult":false},"GAMSSourceFolder":"GAMS_SrcTIMES.v4.7.0","Name":"NZ10_2055A_10EESSNXCTSC","ParametricGroup":null,"ParametricGroupId":null,"PeriodsDefinition":"pdef-70","PropertiesGroup":"DefaultProperties","PropertiesGroupId":3,"RegionGroup":"AllRegion","RegionGroupId":2,"ScenarioGroup":"NZ10_2055A_10EESSNXCTSC","ScenarioGroupId":50,"Solver":"cplex","SolverOptionFile":"2BS_Con_Aut","UserName":"bruno"},{"CaseId":13,"CreatedOn":"2024-01-25 18:40","Description":"","EditedOn":"2024-02-01 19:21","EndingYear":"2068","FixResultFileName":"False","FixResultInfo":{"WorkTimesFolderPath":null,"GdxElasticDermands":{"GdxSelectedFile":{"FileName":"","FilePath":"","IsSelected":false},"IsApplied":false},"GdxIre":{"GdxSelectedFile":{"FileName":"","FilePath":"","IsSelected":false},"IsApplied":false,"RadioSelection":1},"GdxUseSolution":{"FixYearsUpto":"","GdxSelectedFile":{"FileName":"","FilePath":"","IsSelected":false},"IsApplied":false,"RadioSelection":1},"IsApplyFixResult":false},"GAMSSourceFolder":"GAMS_SrcTIMES.v4.7.0","Name":"NZ10_2055A_10EESSEXCTSC","ParametricGroup":null,"ParametricGroupId":null,"PeriodsDefinition":"pdef-70","PropertiesGroup":"DefaultProperties","PropertiesGroupId":3,"RegionGroup":"AllRegion","RegionGroupId":2,"ScenarioGroup":"NZ10_2055A_10EESSEXCTSC","ScenarioGroupId":13,"Solver":"cplex","SolverOptionFile":"2BS_Con_Aut","UserName":"bruno"},{"CaseId":14,"CreatedOn":"2024-01-25 18:41","Description":"","EditedOn":"2024-02-01 19:21","EndingYear":"2068","FixResultFileName":"False","FixResultInfo":{"WorkTimesFolderPath":null,"GdxElasticDermands":{"GdxSelectedFile":{"FileName":"","FilePath":"","IsSelected":false},"IsApplied":false},"GdxIre":{"GdxSelectedFile":{"FileName":"","FilePath":"","IsSelected":false},"IsApplied":false,"RadioSelection":1},"GdxUseSolution":{"FixYearsUpto":"","GdxSelectedFile":{"FileName":"","FilePath":"","IsSelected":false},"IsApplied":false,"RadioSelection":1},"IsApplyFixResult":false},"GAMSSourceFolder":"GAMS_SrcTIMES.v4.7.0","Name":"NZ10_2055A_09EESSNXCTSC","ParametricGroup":null,"ParametricGroupId":null,"PeriodsDefinition":"pdef-70","PropertiesGroup":"DefaultProperties","PropertiesGroupId":3,"RegionGroup":"AllRegion","RegionGroupId":2,"ScenarioGroup":"NZ10_2055A_09EESSNXCTSC","ScenarioGroupId":18,"Solver":"cplex","SolverOptionFile":"2BS_Con_Aut","UserName":"bruno"},{"CaseId":15,"CreatedOn":"2024-01-25 18:42","Description":"","EditedOn":"2024-02-01 19:21","EndingYear":"2068","FixResultFileName":"False","FixResultInfo":{"WorkTimesFolderPath":null,"GdxElasticDermands":{"GdxSelectedFile":{"FileName":"","FilePath":"","IsSelected":false},"IsApplied":false},"GdxIre":{"GdxSelectedFile":{"FileName":"","FilePath":"","IsSelected":false},"IsApplied":false,"RadioSelection":1},"GdxUseSolution":{"FixYearsUpto":"","GdxSelectedFile":{"FileName":"","FilePath":"","IsSelected":false},"IsApplied":false,"RadioSelection":1},"IsApplyFixResult":false},"GAMSSourceFolder":"GAMS_SrcTIMES.v4.7.0","Name":"NZ10_2050B_11EESSNXCNSC","ParametricGroup":null,"ParametricGroupId":null,"PeriodsDefinition":"pdef-70","PropertiesGroup":"DefaultProperties","PropertiesGroupId":3,"RegionGroup":"AllRegion","RegionGroupId":2,"ScenarioGroup":"NZ10_2050B_11EESSNXCNSC","ScenarioGroupId":20,"Solver":"cplex","SolverOptionFile":"2BS_Con_Aut","UserName":"bruno"},{"CaseId":16,"CreatedOn":"2024-01-25 18:43","Description":"","EditedOn":"2024-02-01 19:21","EndingYear":"2068","FixResultFileName":"False","FixResultInfo":{"WorkTimesFolderPath":null,"GdxElasticDermands":{"GdxSelectedFile":{"FileName":"","FilePath":"","IsSelected":false},"IsApplied":false},"GdxIre":{"GdxSelectedFile":{"FileName":"","FilePath":"","IsSelected":false},"IsApplied":false,"RadioSelection":1},"GdxUseSolution":{"FixYearsUpto":"","GdxSelectedFile":{"FileName":"","FilePath":"","IsSelected":false},"IsApplied":false,"RadioSelection":1},"IsApplyFixResult":false},"GAMSSourceFolder":"GAMS_SrcTIMES.v4.7.0","Name":"NZ10_2050B_09EESSNXCNSC","ParametricGroup":null,"ParametricGroupId":null,"PeriodsDefinition":"pdef-70","PropertiesGroup":"DefaultProperties","PropertiesGroupId":3,"RegionGroup":"AllRegion","RegionGroupId":2,"ScenarioGroup":"NZ10_2050B_09EESSNXCNSC","ScenarioGroupId":14,"Solver":"cplex","SolverOptionFile":"2BS_Con_Aut","UserName":"bruno"},{"CaseId":17,"CreatedOn":"2024-01-25 18:44","Description":"","EditedOn":"2024-02-01 19:21","EndingYear":"2068","FixResultFileName":"False","FixResultInfo":{"WorkTimesFolderPath":null,"GdxElasticDermands":{"GdxSelectedFile":{"FileName":"","FilePath":"","IsSelected":false},"IsApplied":false},"GdxIre":{"GdxSelectedFile":{"FileName":"","FilePath":"","IsSelected":false},"IsApplied":false,"RadioSelection":1},"GdxUseSolution":{"FixYearsUpto":"","GdxSelectedFile":{"FileName":"","FilePath":"","IsSelected":false},"IsApplied":false,"RadioSelection":1},"IsApplyFixResult":false},"GAMSSourceFolder":"GAMS_SrcTIMES.v4.7.0","Name":"NZ10_2050B_09EESSEXCNSC","ParametricGroup":null,"ParametricGroupId":null,"PeriodsDefinition":"pdef-70","PropertiesGroup":"DefaultProperties","PropertiesGroupId":3,"RegionGroup":"AllRegion","RegionGroupId":2,"ScenarioGroup":"NZ10_2050B_09EESSEXCNSC","ScenarioGroupId":21,"Solver":"cplex","SolverOptionFile":"2BS_Con_Aut","UserName":"bruno"},{"CaseId":18,"CreatedOn":"2024-01-25 18:45","Description":"","EditedOn":"2024-02-01 19:21","EndingYear":"2068","FixResultFileName":"False","FixResultInfo":{"WorkTimesFolderPath":null,"GdxElasticDermands":{"GdxSelectedFile":{"FileName":"","FilePath":"","IsSelected":false},"IsApplied":false},"GdxIre":{"GdxSelectedFile":{"FileName":"","FilePath":"","IsSelected":false},"IsApplied":false,"RadioSelection":1},"GdxUseSolution":{"FixYearsUpto":"","GdxSelectedFile":{"FileName":"","FilePath":"","IsSelected":false},"IsApplied":false,"RadioSelection":1},"IsApplyFixResult":false},"GAMSSourceFolder":"GAMS_SrcTIMES.v4.7.0","Name":"NZ10_2050A_99EESSNXCTSC","ParametricGroup":null,"ParametricGroupId":null,"PeriodsDefinition":"pdef-70","PropertiesGroup":"DefaultProperties","PropertiesGroupId":3,"RegionGroup":"AllRegion","RegionGroupId":2,"ScenarioGroup":"NZ10_2050A_99EESSNXCTSC","ScenarioGroupId":23,"Solver":"cplex","SolverOptionFile":"2BS_Con_Aut","UserName":"bruno"},{"CaseId":19,"CreatedOn":"2024-01-25 18:46","Description":"","EditedOn":"2024-02-01 19:21","EndingYear":"2068","FixResultFileName":"False","FixResultInfo":{"WorkTimesFolderPath":null,"GdxElasticDermands":{"GdxSelectedFile":{"FileName":"","FilePath":"","IsSelected":false},"IsApplied":false},"GdxIre":{"GdxSelectedFile":{"FileName":"","FilePath":"","IsSelected":false},"IsApplied":false,"RadioSelection":1},"GdxUseSolution":{"FixYearsUpto":"","GdxSelectedFile":{"FileName":"","FilePath":"","IsSelected":false},"IsApplied":false,"RadioSelection":1},"IsApplyFixResult":false},"GAMSSourceFolder":"GAMS_SrcTIMES.v4.7.0","Name":"NZ10_2050A_11EESSNXCTSC","ParametricGroup":null,"ParametricGroupId":null,"PeriodsDefinition":"pdef-70","PropertiesGroup":"DefaultProperties","PropertiesGroupId":3,"RegionGroup":"AllRegion","RegionGroupId":2,"ScenarioGroup":"NZ10_2050A_11EESSNXCTSC","ScenarioGroupId":24,"Solver":"cplex","SolverOptionFile":"2BS_Con_Aut","UserName":"bruno"},{"CaseId":20,"CreatedOn":"2024-01-25 18:50","Description":"","EditedOn":"2024-02-01 19:21","EndingYear":"2068","FixResultFileName":"False","FixResultInfo":{"WorkTimesFolderPath":null,"GdxElasticDermands":{"GdxSelectedFile":{"FileName":"","FilePath":"","IsSelected":false},"IsApplied":false},"GdxIre":{"GdxSelectedFile":{"FileName":"","FilePath":"","IsSelected":false},"IsApplied":false,"RadioSelection":1},"GdxUseSolution":{"FixYearsUpto":"","GdxSelectedFile":{"FileName":"","FilePath":"","IsSelected":false},"IsApplied":false,"RadioSelection":1},"IsApplyFixResult":false},"GAMSSourceFolder":"GAMS_SrcTIMES.v4.7.0","Name":"NZ10_2050A_10EESSNXCTSC","ParametricGroup":null,"ParametricGroupId":null,"PeriodsDefinition":"pdef-70","PropertiesGroup":"DefaultProperties","PropertiesGroupId":3,"RegionGroup":"AllRegion","RegionGroupId":2,"ScenarioGroup":"NZ10_2050A_10EESSNXCTSC","ScenarioGroupId":25,"Solver":"cplex","SolverOptionFile":"2BS_Con_Aut","UserName":"bruno"},{"CaseId":21,"CreatedOn":"2024-01-25 18:51","Description":"","EditedOn":"2024-02-01 19:21","EndingYear":"2068","FixResultFileName":"False","FixResultInfo":{"WorkTimesFolderPath":null,"GdxElasticDermands":{"GdxSelectedFile":{"FileName":"","FilePath":"","IsSelected":false},"IsApplied":false},"GdxIre":{"GdxSelectedFile":{"FileName":"","FilePath":"","IsSelected":false},"IsApplied":false,"RadioSelection":1},"GdxUseSolution":{"FixYearsUpto":"","GdxSelectedFile":{"FileName":"","FilePath":"","IsSelected":false},"IsApplied":false,"RadioSelection":1},"IsApplyFixResult":false},"GAMSSourceFolder":"GAMS_SrcTIMES.v4.7.0","Name":"NZ10_2050A_09NESSNXCTSC","ParametricGroup":null,"ParametricGroupId":null,"PeriodsDefinition":"pdef-70","PropertiesGroup":"DefaultProperties","PropertiesGroupId":3,"RegionGroup":"AllRegion","RegionGroupId":2,"ScenarioGroup":"NZ10_2050A_09NESSNXCTSC","ScenarioGroupId":26,"Solver":"cplex","SolverOptionFile":"2BS_Con_Aut","UserName":"bruno"},{"CaseId":22,"CreatedOn":"2024-01-25 18:51","Description":"","EditedOn":"2024-02-01 19:21","EndingYear":"2068","FixResultFileName":"False","FixResultInfo":{"WorkTimesFolderPath":null,"GdxElasticDermands":{"GdxSelectedFile":{"FileName":"","FilePath":"","IsSelected":false},"IsApplied":false},"GdxIre":{"GdxSelectedFile":{"FileName":"","FilePath":"","IsSelected":false},"IsApplied":false,"RadioSelection":1},"GdxUseSolution":{"FixYearsUpto":"","GdxSelectedFile":{"FileName":"","FilePath":"","IsSelected":false},"IsApplied":false,"RadioSelection":1},"IsApplyFixResult":false},"GAMSSourceFolder":"GAMS_SrcTIMES.v4.7.0","Name":"NZ10_2050A_09EESSNXCTSC","ParametricGroup":null,"ParametricGroupId":null,"PeriodsDefinition":"pdef-70","PropertiesGroup":"DefaultProperties","PropertiesGroupId":3,"RegionGroup":"AllRegion","RegionGroupId":2,"ScenarioGroup":"NZ10_2050A_09EESSNXCTSC","ScenarioGroupId":27,"Solver":"cplex","SolverOptionFile":"2BS_Con_Aut","UserName":"bruno"},{"CaseId":23,"CreatedOn":"2024-01-25 18:52","Description":"","EditedOn":"2024-02-01 19:21","EndingYear":"2068","FixResultFileName":"False","FixResultInfo":{"WorkTimesFolderPath":null,"GdxElasticDermands":{"GdxSelectedFile":{"FileName":"","FilePath":"","IsSelected":false},"IsApplied":false},"GdxIre":{"GdxSelectedFile":{"FileName":"","FilePath":"","IsSelected":false},"IsApplied":false,"RadioSelection":1},"GdxUseSolution":{"FixYearsUpto":"","GdxSelectedFile":{"FileName":"","FilePath":"","IsSelected":false},"IsApplied":false,"RadioSelection":1},"IsApplyFixResult":false},"GAMSSourceFolder":"GAMS_SrcTIMES.v4.7.0","Name":"NZ10_2050A_09EESSNXCTCL","ParametricGroup":null,"ParametricGroupId":null,"PeriodsDefinition":"pdef-70","PropertiesGroup":"DefaultProperties","PropertiesGroupId":3,"RegionGroup":"AllRegion","RegionGroupId":2,"ScenarioGroup":"NZ10_2050A_09EESSNXCTCL","ScenarioGroupId":28,"Solver":"cplex","SolverOptionFile":"2BS_Con_Aut","UserName":"bruno"},{"CaseId":24,"CreatedOn":"2024-01-25 18:54","Description":"","EditedOn":"2024-02-01 19:21","EndingYear":"2068","FixResultFileName":"False","FixResultInfo":{"WorkTimesFolderPath":null,"GdxElasticDermands":{"GdxSelectedFile":{"FileName":"","FilePath":"","IsSelected":false},"IsApplied":false},"GdxIre":{"GdxSelectedFile":{"FileName":"","FilePath":"","IsSelected":false},"IsApplied":false,"RadioSelection":1},"GdxUseSolution":{"FixYearsUpto":"","GdxSelectedFile":{"FileName":"","FilePath":"","IsSelected":false},"IsApplied":false,"RadioSelection":1},"IsApplyFixResult":false},"GAMSSourceFolder":"GAMS_SrcTIMES.v4.7.0","Name":"NZ10_2050A_09EESSEXCTSC","ParametricGroup":null,"ParametricGroupId":null,"PeriodsDefinition":"pdef-70","PropertiesGroup":"DefaultProperties","PropertiesGroupId":3,"RegionGroup":"AllRegion","RegionGroupId":2,"ScenarioGroup":"NZ10_2050A_09EESSEXCTSC","ScenarioGroupId":29,"Solver":"cplex","SolverOptionFile":"2BS_Con_Aut","UserName":"bruno"},{"CaseId":25,"CreatedOn":"2024-01-25 18:55","Description":"","EditedOn":"2024-02-01 19:21","EndingYear":"2068","FixResultFileName":"False","FixResultInfo":{"WorkTimesFolderPath":null,"GdxElasticDermands":{"GdxSelectedFile":{"FileName":"","FilePath":"","IsSelected":false},"IsApplied":false},"GdxIre":{"GdxSelectedFile":{"FileName":"","FilePath":"","IsSelected":false},"IsApplied":false,"RadioSelection":1},"GdxUseSolution":{"FixYearsUpto":"","GdxSelectedFile":{"FileName":"","FilePath":"","IsSelected":false},"IsApplied":false,"RadioSelection":1},"IsApplyFixResult":false},"GAMSSourceFolder":"GAMS_SrcTIMES.v4.7.0","Name":"NZ10_2050A_09EESFNXCTSC","ParametricGroup":null,"ParametricGroupId":null,"PeriodsDefinition":"pdef-70","PropertiesGroup":"DefaultProperties","PropertiesGroupId":3,"RegionGroup":"AllRegion","RegionGroupId":2,"ScenarioGroup":"NZ10_2050A_09EESFNXCTSC","ScenarioGroupId":31,"Solver":"cplex","SolverOptionFile":"2BS_Con_Aut","UserName":"bruno"},{"CaseId":26,"CreatedOn":"2024-01-25 18:56","Description":"","EditedOn":"2024-02-01 19:21","EndingYear":"2068","FixResultFileName":"False","FixResultInfo":{"WorkTimesFolderPath":null,"GdxElasticDermands":{"GdxSelectedFile":{"FileName":"","FilePath":"","IsSelected":false},"IsApplied":false},"GdxIre":{"GdxSelectedFile":{"FileName":"","FilePath":"","IsSelected":false},"IsApplied":false,"RadioSelection":1},"GdxUseSolution":{"FixYearsUpto":"","GdxSelectedFile":{"FileName":"","FilePath":"","IsSelected":false},"IsApplied":false,"RadioSelection":1},"IsApplyFixResult":false},"GAMSSourceFolder":"GAMS_SrcTIMES.v4.7.0","Name":"NZ10_2050A_09EESENXCTSC","ParametricGroup":null,"ParametricGroupId":null,"PeriodsDefinition":"pdef-70","PropertiesGroup":"DefaultProperties","PropertiesGroupId":3,"RegionGroup":"AllRegion","RegionGroupId":2,"ScenarioGroup":"NZ10_2050A_09EESENXCTSC","ScenarioGroupId":64,"Solver":"cplex","SolverOptionFile":"2BS_Con_Aut","UserName":"bruno"},{"CaseId":27,"CreatedOn":"2024-01-25 18:57","Description":"","EditedOn":"2024-02-01 19:21","EndingYear":"2068","FixResultFileName":"False","FixResultInfo":{"WorkTimesFolderPath":null,"GdxElasticDermands":{"GdxSelectedFile":{"FileName":"","FilePath":"","IsSelected":false},"IsApplied":false},"GdxIre":{"GdxSelectedFile":{"FileName":"","FilePath":"","IsSelected":false},"IsApplied":false,"RadioSelection":1},"GdxUseSolution":{"FixYearsUpto":"","GdxSelectedFile":{"FileName":"","FilePath":"","IsSelected":false},"IsApplied":false,"RadioSelection":1},"IsApplyFixResult":false},"GAMSSourceFolder":"GAMS_SrcTIMES.v4.7.0","Name":"NZ10_2050A_08EESSNXCTSC","ParametricGroup":null,"ParametricGroupId":null,"PeriodsDefinition":"pdef-70","PropertiesGroup":"DefaultProperties","PropertiesGroupId":3,"RegionGroup":"AllRegion","RegionGroupId":2,"ScenarioGroup":"NZ10_2050A_08EESSNXCTSC","ScenarioGroupId":32,"Solver":"cplex","SolverOptionFile":"2BS_Con_Aut","UserName":"bruno"},{"CaseId":28,"CreatedOn":"2024-01-26 08:25","Description":"","EditedOn":"2024-02-01 19:21","EndingYear":"2068","FixResultFileName":"False","FixResultInfo":{"WorkTimesFolderPath":null,"GdxElasticDermands":{"GdxSelectedFile":{"FileName":"","FilePath":"","IsSelected":false},"IsApplied":false},"GdxIre":{"GdxSelectedFile":{"FileName":"","FilePath":"","IsSelected":false},"IsApplied":false,"RadioSelection":1},"GdxUseSolution":{"FixYearsUpto":"","GdxSelectedFile":{"FileName":"","FilePath":"","IsSelected":false},"IsApplied":false,"RadioSelection":1},"IsApplyFixResult":false},"GAMSSourceFolder":"GAMS_SrcTIMES.v4.7.0","Name":"NZ10_2099A_99EESSNXCTCL","ParametricGroup":null,"ParametricGroupId":null,"PeriodsDefinition":"pdef-70","PropertiesGroup":"DefaultProperties","PropertiesGroupId":3,"RegionGroup":"AllRegion","RegionGroupId":2,"ScenarioGroup":"NZ10_2099A_99EESSNXCTCL","ScenarioGroupId":33,"Solver":"cplex","SolverOptionFile":"2BS_Con_Aut","UserName":"bruno"},{"CaseId":29,"CreatedOn":"2024-01-26 11:09","Description":"","EditedOn":"2024-02-01 19:21","EndingYear":"2068","FixResultFileName":"False","FixResultInfo":{"WorkTimesFolderPath":null,"GdxElasticDermands":{"GdxSelectedFile":{"FileName":"","FilePath":"","IsSelected":false},"IsApplied":false},"GdxIre":{"GdxSelectedFile":{"FileName":"","FilePath":"","IsSelected":false},"IsApplied":false,"RadioSelection":1},"GdxUseSolution":{"FixYearsUpto":"","GdxSelectedFile":{"FileName":"","FilePath":"","IsSelected":false},"IsApplied":false,"RadioSelection":1},"IsApplyFixResult":false},"GAMSSourceFolder":"GAMS_SrcTIMES.v4.7.0","Name":"NZ10_2099A_99EESSNXCTSC","ParametricGroup":null,"ParametricGroupId":null,"PeriodsDefinition":"pdef-70","PropertiesGroup":"DefaultProperties","PropertiesGroupId":3,"RegionGroup":"AllRegion","RegionGroupId":2,"ScenarioGroup":"NZ10_2099A_99EESSNXCTSC","ScenarioGroupId":36,"Solver":"cplex","SolverOptionFile":"2BS_Con_Aut","UserName":"bruno"},{"CaseId":30,"CreatedOn":"2024-01-30 12:20","Description":"","EditedOn":"2024-02-01 19:21","EndingYear":"2068","FixResultFileName":"False","FixResultInfo":{"WorkTimesFolderPath":null,"GdxElasticDermands":{"GdxSelectedFile":{"FileName":"","FilePath":"","IsSelected":false},"IsApplied":false},"GdxIre":{"GdxSelectedFile":{"FileName":"","FilePath":"","IsSelected":false},"IsApplied":false,"RadioSelection":1},"GdxUseSolution":{"FixYearsUpto":"","GdxSelectedFile":{"FileName":"","FilePath":"","IsSelected":false},"IsApplied":false,"RadioSelection":1},"IsApplyFixResult":false},"GAMSSourceFolder":"GAMS_SrcTIMES.v4.7.0","Name":"NZ10_2099B_99NESSNXCTCLNR","ParametricGroup":null,"ParametricGroupId":null,"PeriodsDefinition":"pdef-70","PropertiesGroup":"DefaultProperties","PropertiesGroupId":3,"RegionGroup":"AllRegion","RegionGroupId":2,"ScenarioGroup":"NZ10_2099B_99NESSNXCTCLNR","ScenarioGroupId":6,"Solver":"cplex","SolverOptionFile":"2BS_Con_Aut","UserName":"bruno"},{"CaseId":31,"CreatedOn":"2024-01-30 14:09","Description":"","EditedOn":"2024-02-01 19:21","EndingYear":"2068","FixResultFileName":"False","FixResultInfo":{"WorkTimesFolderPath":null,"GdxElasticDermands":{"GdxSelectedFile":{"FileName":"","FilePath":"","IsSelected":false},"IsApplied":false},"GdxIre":{"GdxSelectedFile":{"FileName":"","FilePath":"","IsSelected":false},"IsApplied":false,"RadioSelection":1},"GdxUseSolution":{"FixYearsUpto":"","GdxSelectedFile":{"FileName":"","FilePath":"","IsSelected":false},"IsApplied":false,"RadioSelection":1},"IsApplyFixResult":false},"GAMSSourceFolder":"GAMS_SrcTIMES.v4.7.0","Name":"NZ10_2099A_99EESSNXCNSCFR","ParametricGroup":null,"ParametricGroupId":null,"PeriodsDefinition":"pdef-70","PropertiesGroup":"DefaultProperties","PropertiesGroupId":3,"RegionGroup":"AllRegion","RegionGroupId":2,"ScenarioGroup":"NZ10_2099A_99EESSNXCNSCFR","ScenarioGroupId":8,"Solver":"cplex","SolverOptionFile":"2BS_Con_Aut","UserName":"bruno"},{"CaseId":32,"CreatedOn":"2024-01-31 10:31","Description":"","EditedOn":"2024-02-01 19:21","EndingYear":"2068","FixResultFileName":"False","FixResultInfo":{"WorkTimesFolderPath":null,"GdxElasticDermands":{"GdxSelectedFile":{"FileName":"","FilePath":"","IsSelected":false},"IsApplied":false},"GdxIre":{"GdxSelectedFile":{"FileName":"","FilePath":"","IsSelected":false},"IsApplied":false,"RadioSelection":1},"GdxUseSolution":{"FixYearsUpto":"","GdxSelectedFile":{"FileName":"","FilePath":"","IsSelected":false},"IsApplied":false,"RadioSelection":1},"IsApplyFixResult":false},"GAMSSourceFolder":"GAMS_SrcTIMES.v4.7.0","Name":"NZ10_2050A_09EESSNXCTCLERNC","ParametricGroup":null,"ParametricGroupId":null,"PeriodsDefinition":"pdef-70","PropertiesGroup":"DefaultProperties","PropertiesGroupId":3,"RegionGroup":"AllRegion","RegionGroupId":2,"ScenarioGroup":"NZ10_2050A_09EESSNXCTCLERNC","ScenarioGroupId":12,"Solver":"cplex","SolverOptionFile":"2BS_Con_Aut","UserName":"bruno"},{"CaseId":33,"CreatedOn":"2024-01-31 10:32","Description":"","EditedOn":"2024-02-06 12:49","EndingYear":"2068","FixResultFileName":"False","FixResultInfo":{"WorkTimesFolderPath":null,"GdxElasticDermands":{"GdxSelectedFile":{"FileName":"","FilePath":"","IsSelected":false},"IsApplied":false},"GdxIre":{"GdxSelectedFile":{"FileName":"","FilePath":"","IsSelected":false},"IsApplied":false,"RadioSelection":1},"GdxUseSolution":{"FixYearsUpto":"","GdxSelectedFile":{"FileName":"","FilePath":"","IsSelected":false},"IsApplied":false,"RadioSelection":1},"IsApplyFixResult":false},"GAMSSourceFolder":"GAMS_SrcTIMES.v4.7.0","Name":"NZ10_2099B_99NESSNXCTCLER_IRP","ParametricGroup":null,"ParametricGroupId":null,"PeriodsDefinition":"pdef-70","PropertiesGroup":"DefaultProperties","PropertiesGroupId":3,"RegionGroup":"AllRegion","RegionGroupId":2,"ScenarioGroup":"NZ10_2099B_99NESSNXCTCLER_IRP","ScenarioGroupId":16,"Solver":"cplex","SolverOptionFile":"2BS_Con_Aut","UserName":"bruno"},{"CaseId":34,"CreatedOn":"2024-01-31 10:32","Description":"","EditedOn":"2024-02-06 12:49","EndingYear":"2068","FixResultFileName":"False","FixResultInfo":{"WorkTimesFolderPath":null,"GdxElasticDermands":{"GdxSelectedFile":{"FileName":"","FilePath":"","IsSelected":false},"IsApplied":false},"GdxIre":{"GdxSelectedFile":{"FileName":"","FilePath":"","IsSelected":false},"IsApplied":false,"RadioSelection":1},"GdxUseSolution":{"FixYearsUpto":"","GdxSelectedFile":{"FileName":"","FilePath":"","IsSelected":false},"IsApplied":false,"RadioSelection":1},"IsApplyFixResult":false},"GAMSSourceFolder":"GAMS_SrcTIMES.v4.7.0","Name":"NZ10_2099B_99NESSNXCTCLNR_IRP","ParametricGroup":null,"ParametricGroupId":null,"PeriodsDefinition":"pdef-70","PropertiesGroup":"DefaultProperties","PropertiesGroupId":3,"RegionGroup":"AllRegion","RegionGroupId":2,"ScenarioGroup":"NZ10_2099B_99NESSNXCTCLNR_IRP","ScenarioGroupId":7,"Solver":"cplex","SolverOptionFile":"2BS_Con_Aut","UserName":"bruno"},{"CaseId":35,"CreatedOn":"2024-01-31 15:40","Description":"","EditedOn":"2024-02-06 12:49","EndingYear":"2068","FixResultFileName":"False","FixResultInfo":{"WorkTimesFolderPath":null,"GdxElasticDermands":{"GdxSelectedFile":{"FileName":"","FilePath":"","IsSelected":false},"IsApplied":false},"GdxIre":{"GdxSelectedFile":{"FileName":"","FilePath":"","IsSelected":false},"IsApplied":false,"RadioSelection":1},"GdxUseSolution":{"FixYearsUpto":"","GdxSelectedFile":{"FileName":"","FilePath":"","IsSelected":false},"IsApplied":false,"RadioSelection":1},"IsApplyFixResult":false},"GAMSSourceFolder":"GAMS_SrcTIMES.v4.7.0","Name":"NZ10_2099B_99NESSNXCTCL_HiR","ParametricGroup":null,"ParametricGroupId":null,"PeriodsDefinition":"pdef-70","PropertiesGroup":"DefaultProperties","PropertiesGroupId":3,"RegionGroup":"AllRegion","RegionGroupId":2,"ScenarioGroup":"NZ10_2099B_99NESSNXCTCL_HiR","ScenarioGroupId":47,"Solver":"cplex","SolverOptionFile":"2BS_Con_Aut","UserName":"bruno"},{"CaseId":36,"CreatedOn":"2024-01-31 15:41","Description":"","EditedOn":"2024-02-06 12:49","EndingYear":"2068","FixResultFileName":"False","FixResultInfo":{"WorkTimesFolderPath":null,"GdxElasticDermands":{"GdxSelectedFile":{"FileName":"","FilePath":"","IsSelected":false},"IsApplied":false},"GdxIre":{"GdxSelectedFile":{"FileName":"","FilePath":"","IsSelected":false},"IsApplied":false,"RadioSelection":1},"GdxUseSolution":{"FixYearsUpto":"","GdxSelectedFile":{"FileName":"","FilePath":"","IsSelected":false},"IsApplied":false,"RadioSelection":1},"IsApplyFixResult":false},"GAMSSourceFolder":"GAMS_SrcTIMES.v4.7.0","Name":"NZ10_2099B_99NESSNXCTCLNR_HiR","ParametricGroup":null,"ParametricGroupId":null,"PeriodsDefinition":"pdef-70","PropertiesGroup":"DefaultProperties","PropertiesGroupId":3,"RegionGroup":"AllRegion","RegionGroupId":2,"ScenarioGroup":"NZ10_2099B_99NESSNXCTCLNR_HiR","ScenarioGroupId":15,"Solver":"cplex","SolverOptionFile":"2BS_Con_Aut","UserName":"bruno"},{"CaseId":37,"CreatedOn":"2024-02-01 11:23","Description":"","EditedOn":"2024-06-13 08:31","EndingYear":"2068","FixResultFileName":"False","FixResultInfo":{"WorkTimesFolderPath":null,"GdxElasticDermands":{"GdxSelectedFile":{"FileName":"","FilePath":"","IsSelected":false},"IsApplied":false},"GdxIre":{"GdxSelectedFile":{"FileName":"","FilePath":"","IsSelected":false},"IsApplied":false,"RadioSelection":1},"GdxUseSolution":{"FixYearsUpto":"","GdxSelectedFile":{"FileName":"","FilePath":"","IsSelected":false},"IsApplied":false,"RadioSelection":1},"IsApplyFixResult":false},"GAMSSourceFolder":"GAMS_SrcTIMES.v4.7.0","Name":"AllScenarios","ParametricGroup":null,"ParametricGroupId":null,"PeriodsDefinition":"pdef-70","PropertiesGroup":"DefaultProperties","PropertiesGroupId":3,"RegionGroup":"AllRegion","RegionGroupId":2,"ScenarioGroup":"AllScenarios","ScenarioGroupId":74,"Solver":"cplex","SolverOptionFile":"2BS_Con_Aut","UserName":"bruno"},{"CaseId":38,"CreatedOn":"2024-02-01 16:14","Description":"","EditedOn":"2024-02-01 19:21","EndingYear":"2068","FixResultFileName":"False","FixResultInfo":{"WorkTimesFolderPath":null,"GdxElasticDermands":{"GdxSelectedFile":{"FileName":"","FilePath":"","IsSelected":false},"IsApplied":false},"GdxIre":{"GdxSelectedFile":{"FileName":"","FilePath":"","IsSelected":false},"IsApplied":false,"RadioSelection":1},"GdxUseSolution":{"FixYearsUpto":"","GdxSelectedFile":{"FileName":"","FilePath":"","IsSelected":false},"IsApplied":false,"RadioSelection":1},"IsApplyFixResult":false},"GAMSSourceFolder":"GAMS_SrcTIMES.v4.7.0","Name":"NZ10_2050A_09EESSNXCTSCERNC","ParametricGroup":null,"ParametricGroupId":null,"PeriodsDefinition":"pdef-70","PropertiesGroup":"DefaultProperties","PropertiesGroupId":3,"RegionGroup":"AllRegion","RegionGroupId":2,"ScenarioGroup":"NZ10_2050A_09EESSNXCTSCERNC","ScenarioGroupId":40,"Solver":"cplex","SolverOptionFile":"2BS_Con_Aut","UserName":"bruno"},{"CaseId":39,"CreatedOn":"2024-02-02 06:34","Description":"","EditedOn":"2024-02-02 06:34","EndingYear":"2068","FixResultFileName":"False","FixResultInfo":{"WorkTimesFolderPath":null,"GdxElasticDermands":{"GdxSelectedFile":{"FileName":"","FilePath":"","IsSelected":false},"IsApplied":false},"GdxIre":{"GdxSelectedFile":{"FileName":"","FilePath":"","IsSelected":false},"IsApplied":false,"RadioSelection":1},"GdxUseSolution":{"FixYearsUpto":"","GdxSelectedFile":{"FileName":"","FilePath":"","IsSelected":false},"IsApplied":false,"RadioSelection":1},"IsApplyFixResult":false},"GAMSSourceFolder":"GAMS_SrcTIMES.v4.7.0","Name":"NZ10_2099A_99EESSNXCTSCFR","ParametricGroup":null,"ParametricGroupId":null,"PeriodsDefinition":"pdef-70","PropertiesGroup":"DefaultProperties","PropertiesGroupId":3,"RegionGroup":"AllRegion","RegionGroupId":2,"ScenarioGroup":"NZ10_2099A_99EESSNXCTSCFR","ScenarioGroupId":37,"Solver":"cplex","SolverOptionFile":"2BS_Con_Aut","UserName":"bruno"},{"CaseId":40,"CreatedOn":"2024-02-02 10:09","Description":"","EditedOn":"2024-02-02 13:33","EndingYear":"2068","FixResultFileName":"False","FixResultInfo":{"WorkTimesFolderPath":null,"GdxElasticDermands":{"GdxSelectedFile":{"FileName":"","FilePath":"","IsSelected":false},"IsApplied":false},"GdxIre":{"GdxSelectedFile":{"FileName":"","FilePath":"","IsSelected":false},"IsApplied":false,"RadioSelection":1},"GdxUseSolution":{"FixYearsUpto":"","GdxSelectedFile":{"FileName":"","FilePath":"","IsSelected":false},"IsApplied":false,"RadioSelection":1},"IsApplyFixResult":false},"GAMSSourceFolder":"GAMS_SrcTIMES.v4.7.0","Name":"CurPolEE","ParametricGroup":null,"ParametricGroupId":null,"PeriodsDefinition":"pdef-70","PropertiesGroup":"DefaultProperties","PropertiesGroupId":3,"RegionGroup":"AllRegion","RegionGroupId":2,"ScenarioGroup":"CurPolEE","ScenarioGroupId":42,"Solver":"cplex","SolverOptionFile":"2BS_Con_Aut","UserName":"bruno"},{"CaseId":41,"CreatedOn":"2024-02-02 10:36","Description":"","EditedOn":"2024-02-05 07:54","EndingYear":"2068","FixResultFileName":"False","FixResultInfo":{"WorkTimesFolderPath":null,"GdxElasticDermands":{"GdxSelectedFile":{"FileName":"","FilePath":"","IsSelected":false},"IsApplied":false},"GdxIre":{"GdxSelectedFile":{"FileName":"","FilePath":"","IsSelected":false},"IsApplied":false,"RadioSelection":1},"GdxUseSolution":{"FixYearsUpto":"","GdxSelectedFile":{"FileName":"","FilePath":"","IsSelected":false},"IsApplied":false,"RadioSelection":1},"IsApplyFixResult":false},"GAMSSourceFolder":"GAMS_SrcTIMES.v4.7.0","Name":"NetZero2050","ParametricGroup":null,"ParametricGroupId":null,"PeriodsDefinition":"pdef-70","PropertiesGroup":"DefaultProperties","PropertiesGroupId":3,"RegionGroup":"AllRegion","RegionGroupId":2,"ScenarioGroup":"NetZero2050","ScenarioGroupId":44,"Solver":"cplex","SolverOptionFile":"2BS_Con_Aut","UserName":"bruno"},{"CaseId":42,"CreatedOn":"2024-02-02 10:37","Description":"","EditedOn":"2024-02-02 13:33","EndingYear":"2068","FixResultFileName":"False","FixResultInfo":{"WorkTimesFolderPath":null,"GdxElasticDermands":{"GdxSelectedFile":{"FileName":"","FilePath":"","IsSelected":false},"IsApplied":false},"GdxIre":{"GdxSelectedFile":{"FileName":"","FilePath":"","IsSelected":false},"IsApplied":false,"RadioSelection":1},"GdxUseSolution":{"FixYearsUpto":"","GdxSelectedFile":{"FileName":"","FilePath":"","IsSelected":false},"IsApplied":false,"RadioSelection":1},"IsApplyFixResult":false},"GAMSSourceFolder":"GAMS_SrcTIMES.v4.7.0","Name":"CurPolNoEE","ParametricGroup":null,"ParametricGroupId":null,"PeriodsDefinition":"pdef-70","PropertiesGroup":"DefaultProperties","PropertiesGroupId":3,"RegionGroup":"AllRegion","RegionGroupId":2,"ScenarioGroup":"CurPolNoEE","ScenarioGroupId":43,"Solver":"cplex","SolverOptionFile":"2BS_Con_Aut","UserName":"bruno"},{"CaseId":43,"CreatedOn":"2024-02-05 07:09","Description":"","EditedOn":"2024-02-05 07:10","EndingYear":"2068","FixResultFileName":"False","FixResultInfo":{"WorkTimesFolderPath":null,"GdxElasticDermands":{"GdxSelectedFile":{"FileName":"","FilePath":"","IsSelected":false},"IsApplied":false},"GdxIre":{"GdxSelectedFile":{"FileName":"","FilePath":"","IsSelected":false},"IsApplied":false,"RadioSelection":1},"GdxUseSolution":{"FixYearsUpto":"","GdxSelectedFile":{"FileName":"","FilePath":"","IsSelected":false},"IsApplied":false,"RadioSelection":1},"IsApplyFixResult":false},"GAMSSourceFolder":"GAMS_SrcTIMES.v4.7.0","Name":"NZ10_2099A_10EESSEXCTSC","ParametricGroup":null,"ParametricGroupId":null,"PeriodsDefinition":"pdef-70","PropertiesGroup":"DefaultProperties","PropertiesGroupId":3,"RegionGroup":"AllRegion","RegionGroupId":2,"ScenarioGroup":"NZ10_2099A_10EESSEXCTSC","ScenarioGroupId":39,"Solver":"cplex","SolverOptionFile":"2BS_Con_Aut","UserName":"bruno"},{"CaseId":44,"CreatedOn":"2024-02-05 07:10","Description":"","EditedOn":"2024-02-05 07:10","EndingYear":"2068","FixResultFileName":"False","FixResultInfo":{"WorkTimesFolderPath":null,"GdxElasticDermands":{"GdxSelectedFile":{"FileName":"","FilePath":"","IsSelected":false},"IsApplied":false},"GdxIre":{"GdxSelectedFile":{"FileName":"","FilePath":"","IsSelected":false},"IsApplied":false,"RadioSelection":1},"GdxUseSolution":{"FixYearsUpto":"","GdxSelectedFile":{"FileName":"","FilePath":"","IsSelected":false},"IsApplied":false,"RadioSelection":1},"IsApplyFixResult":false},"GAMSSourceFolder":"GAMS_SrcTIMES.v4.7.0","Name":"NZ10_2099A_10EESSNXCTSC","ParametricGroup":null,"ParametricGroupId":null,"PeriodsDefinition":"pdef-70","PropertiesGroup":"DefaultProperties","PropertiesGroupId":3,"RegionGroup":"AllRegion","RegionGroupId":2,"ScenarioGroup":"NZ10_2099A_10EESSNXCTSC","ScenarioGroupId":38,"Solver":"cplex","SolverOptionFile":"2BS_Con_Aut","UserName":"bruno"},{"CaseId":45,"CreatedOn":"2024-02-05 07:53","Description":"","EditedOn":"2024-03-15 13:35","EndingYear":"2068","FixResultFileName":"False","FixResultInfo":{"WorkTimesFolderPath":null,"GdxElasticDermands":{"GdxSelectedFile":{"FileName":"","FilePath":"","IsSelected":false},"IsApplied":false},"GdxIre":{"GdxSelectedFile":{"FileName":"","FilePath":"","IsSelected":false},"IsApplied":false,"RadioSelection":1},"GdxUseSolution":{"FixYearsUpto":"","GdxSelectedFile":{"FileName":"","FilePath":"","IsSelected":false},"IsApplied":false,"RadioSelection":1},"IsApplyFixResult":false},"GAMSSourceFolder":"GAMS_SrcTIMES.v4.7.0","Name":"CurPolCnstOilPrice","ParametricGroup":null,"ParametricGroupId":null,"PeriodsDefinition":"pdef-70","PropertiesGroup":"DefaultProperties","PropertiesGroupId":3,"RegionGroup":"AllRegion","RegionGroupId":2,"ScenarioGroup":"CurPolCnstOilPrice","ScenarioGroupId":68,"Solver":"cplex","SolverOptionFile":"2BS_Con_Aut","UserName":"bruno"},{"CaseId":46,"CreatedOn":"2024-02-05 07:58","Description":"","EditedOn":"2024-02-06 07:37","EndingYear":"2068","FixResultFileName":"False","FixResultInfo":{"WorkTimesFolderPath":null,"GdxElasticDermands":{"GdxSelectedFile":{"FileName":"","FilePath":"","IsSelected":false},"IsApplied":false},"GdxIre":{"GdxSelectedFile":{"FileName":"","FilePath":"","IsSelected":false},"IsApplied":false,"RadioSelection":1},"GdxUseSolution":{"FixYearsUpto":"","GdxSelectedFile":{"FileName":"","FilePath":"","IsSelected":false},"IsApplied":false,"RadioSelection":1},"IsApplyFixResult":false},"GAMSSourceFolder":"GAMS_SrcTIMES.v4.7.0","Name":"NZ10_2099B_10EESSNXCTSC","ParametricGroup":null,"ParametricGroupId":null,"PeriodsDefinition":"pdef-70","PropertiesGroup":"DefaultProperties","PropertiesGroupId":3,"RegionGroup":"AllRegion","RegionGroupId":2,"ScenarioGroup":"NZ10_2099B_10EESSNXCTSC","ScenarioGroupId":45,"Solver":"cplex","SolverOptionFile":"2BS_Con_Aut","UserName":"bruno"},{"CaseId":47,"CreatedOn":"2024-02-06 09:53","Description":"","EditedOn":"2024-02-06 09:53","EndingYear":"2068","FixResultFileName":"False","FixResultInfo":{"WorkTimesFolderPath":null,"GdxElasticDermands":{"GdxSelectedFile":{"FileName":"","FilePath":"","IsSelected":false},"IsApplied":false},"GdxIre":{"GdxSelectedFile":{"FileName":"","FilePath":"","IsSelected":false},"IsApplied":false,"RadioSelection":1},"GdxUseSolution":{"FixYearsUpto":"","GdxSelectedFile":{"FileName":"","FilePath":"","IsSelected":false},"IsApplied":false,"RadioSelection":1},"IsApplyFixResult":false},"GAMSSourceFolder":"GAMS_SrcTIMES.v4.7.0","Name":"NZ10_2050A_08EESSNXCTCL","ParametricGroup":null,"ParametricGroupId":null,"PeriodsDefinition":"pdef-70","PropertiesGroup":"DefaultProperties","PropertiesGroupId":3,"RegionGroup":"AllRegion","RegionGroupId":2,"ScenarioGroup":"NZ10_2050A_08EESSNXCTCL","ScenarioGroupId":41,"Solver":"cplex","SolverOptionFile":"2BS_Con_Aut","UserName":"bruno"},{"CaseId":48,"CreatedOn":"2024-02-07 06:25","Description":"","EditedOn":"2024-02-07 06:25","EndingYear":"2068","FixResultFileName":"False","FixResultInfo":{"WorkTimesFolderPath":null,"GdxElasticDermands":{"GdxSelectedFile":{"FileName":"","FilePath":"","IsSelected":false},"IsApplied":false},"GdxIre":{"GdxSelectedFile":{"FileName":"","FilePath":"","IsSelected":false},"IsApplied":false,"RadioSelection":1},"GdxUseSolution":{"FixYearsUpto":"","GdxSelectedFile":{"FileName":"","FilePath":"","IsSelected":false},"IsApplied":false,"RadioSelection":1},"IsApplyFixResult":false},"GAMSSourceFolder":"GAMS_SrcTIMES.v4.7.0","Name":"NetZero2050CnstOilPrice","ParametricGroup":null,"ParametricGroupId":null,"PeriodsDefinition":"pdef-70","PropertiesGroup":"DefaultProperties","PropertiesGroupId":3,"RegionGroup":"AllRegion","RegionGroupId":2,"ScenarioGroup":"NetZero2050CnstOilPrice","ScenarioGroupId":48,"Solver":"cplex","SolverOptionFile":"2BS_Con_Aut","UserName":"bruno"},{"CaseId":49,"CreatedOn":"2024-02-15 07:35","Description":"","EditedOn":"2024-02-15 07:35","EndingYear":"2068","FixResultFileName":"False","FixResultInfo":{"WorkTimesFolderPath":null,"GdxElasticDermands":{"GdxSelectedFile":{"FileName":"","FilePath":"","IsSelected":false},"IsApplied":false},"GdxIre":{"GdxSelectedFile":{"FileName":"","FilePath":"","IsSelected":false},"IsApplied":false,"RadioSelection":1},"GdxUseSolution":{"FixYearsUpto":"","GdxSelectedFile":{"FileName":"","FilePath":"","IsSelected":false},"IsApplied":false,"RadioSelection":1},"IsApplyFixResult":false},"GAMSSourceFolder":"GAMS_SrcTIMES.v4.7.0","Name":"Delayed","ParametricGroup":null,"ParametricGroupId":null,"PeriodsDefinition":"pdef-70","PropertiesGroup":"DefaultProperties","PropertiesGroupId":3,"RegionGroup":"AllRegion","RegionGroupId":2,"ScenarioGroup":"Delayed","ScenarioGroupId":49,"Solver":"cplex","SolverOptionFile":"2BS_Con_Aut","UserName":"bruno"},{"CaseId":50,"CreatedOn":"2024-02-15 07:55","Description":"","EditedOn":"2024-02-15 07:56","EndingYear":"2068","FixResultFileName":"False","FixResultInfo":{"WorkTimesFolderPath":null,"GdxElasticDermands":{"GdxSelectedFile":{"FileName":"","FilePath":"","IsSelected":false},"IsApplied":false},"GdxIre":{"GdxSelectedFile":{"FileName":"","FilePath":"","IsSelected":false},"IsApplied":false,"RadioSelection":1},"GdxUseSolution":{"FixYearsUpto":"","GdxSelectedFile":{"FileName":"","FilePath":"","IsSelected":false},"IsApplied":false,"RadioSelection":1},"IsApplyFixResult":false},"GAMSSourceFolder":"GAMS_SrcTIMES.v4.7.0","Name":"Delayed_wTax","ParametricGroup":null,"ParametricGroupId":null,"PeriodsDefinition":"pdef-70","PropertiesGroup":"DefaultProperties","PropertiesGroupId":3,"RegionGroup":"AllRegion","RegionGroupId":2,"ScenarioGroup":"Delayed_wTax","ScenarioGroupId":51,"Solver":"cplex","SolverOptionFile":"2BS_Con_Aut","UserName":"bruno"},{"CaseId":51,"CreatedOn":"2024-02-15 10:19","Description":"","EditedOn":"2024-02-23 15:15","EndingYear":"2068","FixResultFileName":"False","FixResultInfo":{"WorkTimesFolderPath":null,"GdxElasticDermands":{"GdxSelectedFile":{"FileName":"","FilePath":"","IsSelected":false},"IsApplied":false},"GdxIre":{"GdxSelectedFile":{"FileName":"","FilePath":"","IsSelected":false},"IsApplied":false,"RadioSelection":1},"GdxUseSolution":{"FixYearsUpto":"","GdxSelectedFile":{"FileName":"","FilePath":"","IsSelected":false},"IsApplied":false,"RadioSelection":1},"IsApplyFixResult":false},"GAMSSourceFolder":"GAMS_SrcTIMES.v4.7.0","Name":"DelayedNZ","ParametricGroup":null,"ParametricGroupId":null,"PeriodsDefinition":"pdef-70","PropertiesGroup":"DefaultProperties","PropertiesGroupId":3,"RegionGroup":"AllRegion","RegionGroupId":2,"ScenarioGroup":"DelayedNZ","ScenarioGroupId":55,"Solver":"cplex","SolverOptionFile":"2BS_Con_Aut","UserName":"bruno"},{"CaseId":52,"CreatedOn":"2024-02-23 10:21","Description":"","EditedOn":"2024-03-14 13:52","EndingYear":"2040","FixResultFileName":"False","FixResultInfo":{"WorkTimesFolderPath":null,"GdxElasticDermands":{"GdxSelectedFile":{"FileName":"","FilePath":"","IsSelected":false},"IsApplied":false},"GdxIre":{"GdxSelectedFile":{"FileName":"","FilePath":"","IsSelected":false},"IsApplied":false,"RadioSelection":1},"GdxUseSolution":{"FixYearsUpto":"","GdxSelectedFile":{"FileName":"","FilePath":"","IsSelected":false},"IsApplied":false,"RadioSelection":1},"IsApplyFixResult":false},"GAMSSourceFolder":"GAMS_SrcTIMES.v4.7.0","Name":"DelayedNZFix","ParametricGroup":null,"ParametricGroupId":null,"PeriodsDefinition":"pdef-40","PropertiesGroup":"DefaultProperties","PropertiesGroupId":3,"RegionGroup":"AllRegion","RegionGroupId":2,"ScenarioGroup":"DelayedNZFix","ScenarioGroupId":56,"Solver":"cplex","SolverOptionFile":"2BS_Con_Aut","UserName":"bruno"},{"CaseId":53,"CreatedOn":"2024-02-28 16:13","Description":"","EditedOn":"2024-02-28 16:41","EndingYear":"2068","FixResultFileName":"False","FixResultInfo":{"WorkTimesFolderPath":null,"GdxElasticDermands":{"GdxSelectedFile":{"FileName":"","FilePath":"","IsSelected":false},"IsApplied":false},"GdxIre":{"GdxSelectedFile":{"FileName":"","FilePath":"","IsSelected":false},"IsApplied":false,"RadioSelection":1},"GdxUseSolution":{"FixYearsUpto":"","GdxSelectedFile":{"FileName":"","FilePath":"","IsSelected":false},"IsApplied":false,"RadioSelection":1},"IsApplyFixResult":false},"GAMSSourceFolder":"GAMS_SrcTIMES.v4.7.0","Name":"NZ10_2055B_09EESSNXCTSC","ParametricGroup":null,"ParametricGroupId":null,"PeriodsDefinition":"pdef-70","PropertiesGroup":"DefaultProperties","PropertiesGroupId":3,"RegionGroup":"AllRegion","RegionGroupId":2,"ScenarioGroup":"NZ10_2055B_09EESSNXCTSC","ScenarioGroupId":60,"Solver":"cplex","SolverOptionFile":"2BS_Con_Aut","UserName":"bruno"},{"CaseId":54,"CreatedOn":"2024-02-28 16:40","Description":"","EditedOn":"2024-02-28 16:41","EndingYear":"2068","FixResultFileName":"False","FixResultInfo":{"WorkTimesFolderPath":null,"GdxElasticDermands":{"GdxSelectedFile":{"FileName":"","FilePath":"","IsSelected":false},"IsApplied":false},"GdxIre":{"GdxSelectedFile":{"FileName":"","FilePath":"","IsSelected":false},"IsApplied":false,"RadioSelection":1},"GdxUseSolution":{"FixYearsUpto":"","GdxSelectedFile":{"FileName":"","FilePath":"","IsSelected":false},"IsApplied":false,"RadioSelection":1},"IsApplyFixResult":false},"GAMSSourceFolder":"GAMS_SrcTIMES.v4.7.0","Name":"NZ10_2050B_09EESFNXCTSC","ParametricGroup":null,"ParametricGroupId":null,"PeriodsDefinition":"pdef-70","PropertiesGroup":"DefaultProperties","PropertiesGroupId":3,"RegionGroup":"AllRegion","RegionGroupId":2,"ScenarioGroup":"NZ10_2050B_09EESFNXCTSC","ScenarioGroupId":66,"Solver":"cplex","SolverOptionFile":"2BS_Con_Aut","UserName":"bruno"},{"CaseId":55,"CreatedOn":"2024-02-28 16:42","Description":"","EditedOn":"2024-02-28 16:42","EndingYear":"2068","FixResultFileName":"False","FixResultInfo":{"WorkTimesFolderPath":null,"GdxElasticDermands":{"GdxSelectedFile":{"FileName":"","FilePath":"","IsSelected":false},"IsApplied":false},"GdxIre":{"GdxSelectedFile":{"FileName":"","FilePath":"","IsSelected":false},"IsApplied":false,"RadioSelection":1},"GdxUseSolution":{"FixYearsUpto":"","GdxSelectedFile":{"FileName":"","FilePath":"","IsSelected":false},"IsApplied":false,"RadioSelection":1},"IsApplyFixResult":false},"GAMSSourceFolder":"GAMS_SrcTIMES.v4.7.0","Name":"NZ10_2050B_09EESENXCTSC","ParametricGroup":null,"ParametricGroupId":null,"PeriodsDefinition":"pdef-70","PropertiesGroup":"DefaultProperties","PropertiesGroupId":3,"RegionGroup":"AllRegion","RegionGroupId":2,"ScenarioGroup":"NZ10_2050B_09EESENXCTSC","ScenarioGroupId":65,"Solver":"cplex","SolverOptionFile":"2BS_Con_Aut","UserName":"bruno"},{"CaseId":56,"CreatedOn":"2024-02-28 16:43","Description":"","EditedOn":"2024-02-28 16:44","EndingYear":"2068","FixResultFileName":"False","FixResultInfo":{"WorkTimesFolderPath":null,"GdxElasticDermands":{"GdxSelectedFile":{"FileName":"","FilePath":"","IsSelected":false},"IsApplied":false},"GdxIre":{"GdxSelectedFile":{"FileName":"","FilePath":"","IsSelected":false},"IsApplied":false,"RadioSelection":1},"GdxUseSolution":{"FixYearsUpto":"","GdxSelectedFile":{"FileName":"","FilePath":"","IsSelected":false},"IsApplied":false,"RadioSelection":1},"IsApplyFixResult":false},"GAMSSourceFolder":"GAMS_SrcTIMES.v4.7.0","Name":"NZ10_2050A_09EESSEXCNSC","ParametricGroup":null,"ParametricGroupId":null,"PeriodsDefinition":"pdef-70","PropertiesGroup":"DefaultProperties","PropertiesGroupId":3,"RegionGroup":"AllRegion","RegionGroupId":2,"ScenarioGroup":"NZ10_2050A_09EESSEXCNSC","ScenarioGroupId":63,"Solver":"cplex","SolverOptionFile":"2BS_Con_Aut","UserName":"bruno"},{"CaseId":57,"CreatedOn":"2024-02-28 16:46","Description":"","EditedOn":"2024-02-28 16:46","EndingYear":"2068","FixResultFileName":"False","FixResultInfo":{"WorkTimesFolderPath":null,"GdxElasticDermands":{"GdxSelectedFile":{"FileName":"","FilePath":"","IsSelected":false},"IsApplied":false},"GdxIre":{"GdxSelectedFile":{"FileName":"","FilePath":"","IsSelected":false},"IsApplied":false,"RadioSelection":1},"GdxUseSolution":{"FixYearsUpto":"","GdxSelectedFile":{"FileName":"","FilePath":"","IsSelected":false},"IsApplied":false,"RadioSelection":1},"IsApplyFixResult":false},"GAMSSourceFolder":"GAMS_SrcTIMES.v4.7.0","Name":"NZ10_2055B_10EESSNXCTSC","ParametricGroup":null,"ParametricGroupId":null,"PeriodsDefinition":"pdef-70","PropertiesGroup":"DefaultProperties","PropertiesGroupId":3,"RegionGroup":"AllRegion","RegionGroupId":2,"ScenarioGroup":"NZ10_2055B_10EESSNXCTSC","ScenarioGroupId":61,"Solver":"cplex","SolverOptionFile":"2BS_Con_Aut","UserName":"bruno"},{"CaseId":58,"CreatedOn":"2024-02-28 16:47","Description":"","EditedOn":"2024-02-28 16:47","EndingYear":"2068","FixResultFileName":"False","FixResultInfo":{"WorkTimesFolderPath":null,"GdxElasticDermands":{"GdxSelectedFile":{"FileName":"","FilePath":"","IsSelected":false},"IsApplied":false},"GdxIre":{"GdxSelectedFile":{"FileName":"","FilePath":"","IsSelected":false},"IsApplied":false,"RadioSelection":1},"GdxUseSolution":{"FixYearsUpto":"","GdxSelectedFile":{"FileName":"","FilePath":"","IsSelected":false},"IsApplied":false,"RadioSelection":1},"IsApplyFixResult":false},"GAMSSourceFolder":"GAMS_SrcTIMES.v4.7.0","Name":"NZ10_2050B_09EESSNXCTSC","ParametricGroup":null,"ParametricGroupId":null,"PeriodsDefinition":"pdef-70","PropertiesGroup":"DefaultProperties","PropertiesGroupId":3,"RegionGroup":"AllRegion","RegionGroupId":2,"ScenarioGroup":"NZ10_2050B_09EESSNXCTSC","ScenarioGroupId":58,"Solver":"cplex","SolverOptionFile":"2BS_Con_Aut","UserName":"bruno"},{"CaseId":59,"CreatedOn":"2024-02-28 16:47","Description":"","EditedOn":"2024-02-28 16:47","EndingYear":"2068","FixResultFileName":"False","FixResultInfo":{"WorkTimesFolderPath":null,"GdxElasticDermands":{"GdxSelectedFile":{"FileName":"","FilePath":"","IsSelected":false},"IsApplied":false},"GdxIre":{"GdxSelectedFile":{"FileName":"","FilePath":"","IsSelected":false},"IsApplied":false,"RadioSelection":1},"GdxUseSolution":{"FixYearsUpto":"","GdxSelectedFile":{"FileName":"","FilePath":"","IsSelected":false},"IsApplied":false,"RadioSelection":1},"IsApplyFixResult":false},"GAMSSourceFolder":"GAMS_SrcTIMES.v4.7.0","Name":"NZ10_2050B_09NESSNXCTCL","ParametricGroup":null,"ParametricGroupId":null,"PeriodsDefinition":"pdef-70","PropertiesGroup":"DefaultProperties","PropertiesGroupId":3,"RegionGroup":"AllRegion","RegionGroupId":2,"ScenarioGroup":"NZ10_2050B_09NESSNXCTCL","ScenarioGroupId":59,"Solver":"cplex","SolverOptionFile":"2BS_Con_Aut","UserName":"bruno"},{"CaseId":60,"CreatedOn":"2024-02-28 16:50","Description":"","EditedOn":"2024-02-28 16:50","EndingYear":"2068","FixResultFileName":"False","FixResultInfo":{"WorkTimesFolderPath":null,"GdxElasticDermands":{"GdxSelectedFile":{"FileName":"","FilePath":"","IsSelected":false},"IsApplied":false},"GdxIre":{"GdxSelectedFile":{"FileName":"","FilePath":"","IsSelected":false},"IsApplied":false,"RadioSelection":1},"GdxUseSolution":{"FixYearsUpto":"","GdxSelectedFile":{"FileName":"","FilePath":"","IsSelected":false},"IsApplied":false,"RadioSelection":1},"IsApplyFixResult":false},"GAMSSourceFolder":"GAMS_SrcTIMES.v4.7.0","Name":"NZ10_2050A_09NESSEXCNCL","ParametricGroup":null,"ParametricGroupId":null,"PeriodsDefinition":"pdef-70","PropertiesGroup":"DefaultProperties","PropertiesGroupId":3,"RegionGroup":"AllRegion","RegionGroupId":2,"ScenarioGroup":"NZ10_2050A_09NESSEXCNCL","ScenarioGroupId":67,"Solver":"cplex","SolverOptionFile":"2BS_Con_Aut","UserName":"bruno"},{"CaseId":61,"CreatedOn":"2024-03-15 13:54","Description":"","EditedOn":"2024-07-23 12:51","EndingYear":"2068","FixResultFileName":"False","FixResultInfo":{"WorkTimesFolderPath":null,"GdxElasticDermands":{"GdxSelectedFile":{"FileName":"","FilePath":"","IsSelected":false},"IsApplied":false},"GdxIre":{"GdxSelectedFile":{"FileName":"","FilePath":"","IsSelected":false},"IsApplied":false,"RadioSelection":1},"GdxUseSolution":{"FixYearsUpto":"","GdxSelectedFile":{"FileName":"","FilePath":"","IsSelected":false},"IsApplied":false,"RadioSelection":1},"IsApplyFixResult":false},"GAMSSourceFolder":"GAMS_SrcTIMES.v4.7.0","Name":"CGECalibScenario","ParametricGroup":null,"ParametricGroupId":null,"PeriodsDefinition":"pdef-70","PropertiesGroup":"DefaultProperties","PropertiesGroupId":3,"RegionGroup":"AllRegion","RegionGroupId":2,"ScenarioGroup":"CGECalibScenario","ScenarioGroupId":69,"Solver":"cplex","SolverOptionFile":"2BS_Con_Aut","UserName":"bruno"},{"CaseId":62,"CreatedOn":"2024-03-19 07:15","Description":"","EditedOn":"2024-03-19 07:15","EndingYear":"2055","FixResultFileName":"False","FixResultInfo":{"WorkTimesFolderPath":null,"GdxElasticDermands":{"GdxSelectedFile":{"FileName":"","FilePath":"","IsSelected":false},"IsApplied":false},"GdxIre":{"GdxSelectedFile":{"FileName":"","FilePath":"","IsSelected":false},"IsApplied":false,"RadioSelection":1},"GdxUseSolution":{"FixYearsUpto":"","GdxSelectedFile":{"FileName":"","FilePath":"","IsSelected":false},"IsApplied":false,"RadioSelection":1},"IsApplyFixResult":false},"GAMSSourceFolder":"GAMS_SrcTIMES.v4.7.0","Name":"CGECalibNRF","ParametricGroup":null,"ParametricGroupId":null,"PeriodsDefinition":"pdef-55","PropertiesGroup":"DefaultProperties","PropertiesGroupId":3,"RegionGroup":"AllRegion","RegionGroupId":2,"ScenarioGroup":"CGECalibNRF","ScenarioGroupId":70,"Solver":"cplex","SolverOptionFile":"2BS_Con_Aut","UserName":"bruno"},{"CaseId":63,"CreatedOn":"2024-03-19 14:08","Description":"","EditedOn":"2024-04-18 09:46","EndingYear":"2030","FixResultFileName":"False","FixResultInfo":{"WorkTimesFolderPath":null,"GdxElasticDermands":{"GdxSelectedFile":{"FileName":"","FilePath":"","IsSelected":false},"IsApplied":false},"GdxIre":{"GdxSelectedFile":{"FileName":"","FilePath":"","IsSelected":false},"IsApplied":false,"RadioSelection":1},"GdxUseSolution":{"FixYearsUpto":"","GdxSelectedFile":{"FileName":"","FilePath":"","IsSelected":false},"IsApplied":false,"RadioSelection":1},"IsApplyFixResult":false},"GAMSSourceFolder":"GAMS_SrcTIMES.v4.7.0","Name":"IRPDemandREF","ParametricGroup":null,"ParametricGroupId":null,"PeriodsDefinition":"pdef-30","PropertiesGroup":"DefaultProperties","PropertiesGroupId":3,"RegionGroup":"AllRegion","RegionGroupId":2,"ScenarioGroup":"IRPDemandREF","ScenarioGroupId":71,"Solver":"cplex","SolverOptionFile":"2BS_Con_Aut","UserName":"bruno"},{"CaseId":64,"CreatedOn":"2024-03-19 15:03","Description":"","EditedOn":"2024-03-19 15:03","EndingYear":"2068","FixResultFileName":"False","FixResultInfo":{"WorkTimesFolderPath":null,"GdxElasticDermands":{"GdxSelectedFile":{"FileName":"","FilePath":"","IsSelected":false},"IsApplied":false},"GdxIre":{"GdxSelectedFile":{"FileName":"","FilePath":"","IsSelected":false},"IsApplied":false,"RadioSelection":1},"GdxUseSolution":{"FixYearsUpto":"","GdxSelectedFile":{"FileName":"","FilePath":"","IsSelected":false},"IsApplied":false,"RadioSelection":1},"IsApplyFixResult":false},"GAMSSourceFolder":"GAMS_SrcTIMES.v4.7.0","Name":"IRPDemandLOW","ParametricGroup":null,"ParametricGroupId":null,"PeriodsDefinition":"pdef-70","PropertiesGroup":"DefaultProperties","PropertiesGroupId":3,"RegionGroup":"AllRegion","RegionGroupId":2,"ScenarioGroup":"IRPDemandLOW","ScenarioGroupId":72,"Solver":"cplex","SolverOptionFile":"2BS_Con_Aut","UserName":"bruno"},{"CaseId":65,"CreatedOn":"2024-03-20 06:43","Description":"","EditedOn":"2024-03-20 06:43","EndingYear":"2068","FixResultFileName":"False","FixResultInfo":{"WorkTimesFolderPath":null,"GdxElasticDermands":{"GdxSelectedFile":{"FileName":"","FilePath":"","IsSelected":false},"IsApplied":false},"GdxIre":{"GdxSelectedFile":{"FileName":"","FilePath":"","IsSelected":false},"IsApplied":false,"RadioSelection":1},"GdxUseSolution":{"FixYearsUpto":"","GdxSelectedFile":{"FileName":"","FilePath":"","IsSelected":false},"IsApplied":false,"RadioSelection":1},"IsApplyFixResult":false},"GAMSSourceFolder":"GAMS_SrcTIMES.v4.7.0","Name":"IRPDemandHIG","ParametricGroup":null,"ParametricGroupId":null,"PeriodsDefinition":"pdef-70","PropertiesGroup":"DefaultProperties","PropertiesGroupId":3,"RegionGroup":"AllRegion","RegionGroupId":2,"ScenarioGroup":"IRPDemandHIG","ScenarioGroupId":73,"Solver":"cplex","SolverOptionFile":"2BS_Con_Aut","UserName":"bruno"}]